ezyfiles/__init__.py
ezyfiles/core.py
ezyfiles/metadata.py
ezyfiles/search.py
ezyfiles/utils.py
tests/__init__.py
tests/test_ezyfiles.py
tests/test_simple.py
ezyfiles-0.1.0.dist-info/METADATA
ezyfiles-0.1.0.dist-info/WHEEL
ezyfiles-0.1.0.dist-info/top_level.txt
ezyfiles-0.1.0.dist-info/RECORD
