Metadata-Version: 2.4
Name: ezyfiles
Version: 0.1.0
Summary: Truly Simple File Operations for Python
Home-page: https://github.com/Raykarr/ezyfiles
Author: Kaustubh Raykar
Author-email: raykarkaustubh@gmail.com
Classifier: Programming Language :: Python :: 3
Classifier: License :: OSI Approved :: MIT License
Classifier: Operating System :: OS Independent
Requires-Python: >=3.6
Requires-Dist: pandas>=1.3.0
Requires-Dist: openpyxl>=3.0.0
Requires-Dist: pyyaml>=6.0
Dynamic: author
Dynamic: author-email
Dynamic: classifier
Dynamic: description
Dynamic: description-content-type
Dynamic: home-page
Dynamic: requires-dist
Dynamic: requires-python
Dynamic: summary
